ringlink-0.1.3.dist-info/METADATA
ringlink-0.1.3.dist-info/WHEEL
ringlink/builder.pyi
ringlink/identity.pyi
ringlink/proxy/tcp.pyi
ringlink/__init__.py
ringlink/__init__.pyi
ringlink/_ringlink.pyd
ringlink-0.1.3.dist-info/RECORD
