Metadata-Version: 2.4
Name: ringlink
Version: 0.1.3
Classifier: Programming Language :: Rust
Classifier: Programming Language :: Python :: Implementation :: CPython
Classifier: Programming Language :: Python :: Implementation :: PyPy
Summary: Python bindings for RingLink
Author-email: boot <boot@ring.link>
Requires-Python: >=3.9
